cellmaps_vnn/__init__.py
cellmaps_vnn/annotate.py
cellmaps_vnn/ccc_loss.py
cellmaps_vnn/cellmaps_vnncmd.py
cellmaps_vnn/constants.py
cellmaps_vnn/data_wrapper.py
cellmaps_vnn/exceptions.py
cellmaps_vnn/importance_score.py
cellmaps_vnn/interactome_style.cx2
cellmaps_vnn/nest_style.cx2
cellmaps_vnn/optuna_vnn_trainer.py
cellmaps_vnn/predict.py
cellmaps_vnn/rlipp_calculator.py
cellmaps_vnn/runner.py
cellmaps_vnn/train.py
cellmaps_vnn/util.py
cellmaps_vnn/vnn.py
cellmaps_vnn/vnn_trainer.py
cellmaps_vnn-0.2.2.data/scripts/cellmaps_vnncmd.py
cellmaps_vnn-0.2.2.dist-info/AUTHORS.rst
cellmaps_vnn-0.2.2.dist-info/LICENSE
cellmaps_vnn-0.2.2.dist-info/METADATA
cellmaps_vnn-0.2.2.dist-info/WHEEL
cellmaps_vnn-0.2.2.dist-info/top_level.txt
cellmaps_vnn-0.2.2.dist-info/RECORD
