Metadata-Version: 2.1
Name: cellmaps_vnn
Version: 0.2.2
Summary: The Cell Maps VNN Tool enables creation, training, and usage of an interpretable neural network-based models that predict cell response to a drug.
Home-page: https://github.com/idekerlab/cellmaps_vnn
Author: Christopher Churas
Author-email: tools@cm4ai.org
License: MIT license
Keywords: cellmaps_vnn
Classifier: Development Status :: 2 - Pre-Alpha
Classifier: Intended Audience :: Developers
Classifier: License :: OSI Approved :: MIT License
Classifier: Natural Language :: English
Classifier: Programming Language :: Python :: 3.8
Classifier: Programming Language :: Python :: 3.9
Classifier: Programming Language :: Python :: 3.10
Classifier: Programming Language :: Python :: 3.11
License-File: LICENSE
License-File: AUTHORS.rst
Requires-Dist: cellmaps-utils <1.0.0,>=0.4.0
Requires-Dist: ndex2 <4.0.0,>=3.8.0
Requires-Dist: optuna <4.0.0,>=3.6.0
Requires-Dist: scikit-learn <1.4.0,>=1.3.0
Requires-Dist: networkx <2.9,>=2.8
Requires-Dist: pandas <3.0.0,>=2.0.0
Requires-Dist: torch <3.0.0,>=2.0.0
Requires-Dist: torchvision <1.0.0,>=0.15.0
Requires-Dist: torchaudio <3.0.0,>=2.0.0
Requires-Dist: scipy <2.0.0,>=1.10.0
Requires-Dist: joblib <2.0.0,>=1.3.2
